vearch/__init__.py
vearch/config.py
vearch/const.py
vearch/exception.py
vearch/filter.py
vearch/result.py
vearch/utils.py
vearch/core/__init__.py
vearch/core/client.py
vearch/core/db.py
vearch/core/space.py
vearch/core/vearch.py
vearch/schema/__init__.py
vearch/schema/field.py
vearch/schema/index.py
vearch/schema/space.py
pyvearch-3.5.5.dist-info/METADATA
pyvearch-3.5.5.dist-info/WHEEL
pyvearch-3.5.5.dist-info/top_level.txt
pyvearch-3.5.5.dist-info/RECORD
